Tomel/__init__.py
Tomel/__main__.py
Tomel/components/__init__.py
Tomel/components/accordion_frame.py
Tomel/components/bullet_points.py
Tomel/components/editor_frame.py
Tomel/components/profile_generator.py
Tomel/components/radar_component.py
Tomel/components/rich_text.py
Tomel/components/slideshow.py
Tomel/components/video_player_frame.py
Tomel/service/__init__.py
Tomel/service/cyber_client.py
Tomel/service/runner.py
Tomel/service/submission_interface.py
Tomel/service/test_asyncio_subprocess.py
Tomel/service/test_vbox.conf
Tomel/service/testing_vbox.py
Tomel/service/virtual_box_cyber_competitive_interaction.py
tomel-0.0.1.dist-info/entry_points.txt
tomel-0.0.1.dist-info/LICENSE
tomel-0.0.1.dist-info/WHEEL
tomel-0.0.1.dist-info/METADATA
tomel-0.0.1.dist-info/RECORD
