Metadata-Version: 2.1
Name: Tomel
Version: 0.0.1
Summary: Placeholder
Author-email: cyberiscv <cyberiscv@gmail.com>
Classifier: License :: OSI Approved :: MIT License
Classifier: Programming Language :: Python :: 3
Requires-Dist: matplotlib
Requires-Dist: pygments
Requires-Dist: numpy
Requires-Dist: tkVideoPlayer
Requires-Dist: pillow
Requires-Dist: aiofile
Requires-Dist: asyncssh
Requires-Dist: virtualbox
Project-URL: Home, https://github.com/cyberiscv/Tomel
